Workbook

Sheet __FDSCACHE__
B1: This sheet contains FactSet XML data for use with this workbook's =FDS codes. Modifying the worksheet's contents may damage the workbook's =FDS functionality.

Sheet Cover Sheet
A1: Facebook Inc. (FB)
A3: Company Model
A5: 42473

Sheet FB Income Statement 
A1: Facebook Inc
B3: A | C3: A | D3: A | E3: A | F3: A | G3: E | H3: E | I3: E
A4: all figures $millions, except per share data | B4: 2011 | C4: 2012 | D4: 2013 | E4: 2014 | F4: 2015 | G4: 2016 | H4: 2017 | I4: 2018
A5: Income Statement
A6: Sales | B6: 3711 | C6: 5089 | D6: 7872 | E6: 12466 | F6: 17927 | G6: =F6*(1+G73) -> 24918.53 | H6: =G6*(1+H73) -> 32394.089 | I6: =H6*(1+I73) -> 39196.848
A7: Cost of Revenue | B7: 860 | C7: 1364 | D7: 1758 | E7: 2187 | F7: 2867 | G7: =G8+G9 -> 3986.9648 | H7: =H8+H9 -> 5183.0542 | I7: =I8+I9 -> 6663.4641
A8: COGS excluding D&A | B8: 537 | C8: 715 | D8: 747 | E8: 944 | F8: 922 | G8: =G6*G78 -> 1495.1118 | H8: =H6*H78 -> 1943.6453 | I8: =I6*I78 -> 2351.8109
A9: Depreciation & Amortization Expense | B9: 323 | C9: 649 | D9: 1011 | E9: 1243 | F9: 1945 | G9: =G77*G6 -> 2491.853 | H9: =H77*H6 -> 3239.4089 | I9: =I77*I6 -> 4311.6532
A10: Depreciation | B10: 303 | C10: 571 | D10: 866 | E10: 924 | F10: 1215
A11: Amortization of Intangibles | B11: 20 | C11: 78 | D11: 145 | E11: 319 | F11: 730
A12: Amortization of Deferred Charges | B12: - | C12: - | D12: - | E12: - | F12: -
A13: Gross Profit | B13: =B6-B7 -> 2851 | C13: =C6-C7 -> 3725 | D13: =D6-D7 -> 6114 | E13: =E6-E7 -> 10279 | F13: =F6-F7 -> 15060 | G13: =G6-G7 -> 20931.565 | H13: =H6-H7 -> 27211.035 | I13: =I6-I7 -> 32533.384
A14: SG&A Expense | B14: 1095 | C14: 3187 | D14: 3193 | E14: 5319 | F14: 8836 | G14: =G76*G6 -> 9967.412 | H14: =H76*H6 -> 13605.517 | I14: =I76*I6 -> 15678.739
A15: Research & Development | B15: 388 | C15: 1399 | D15: 1415 | E15: 2666 | F15: 4816 | G15: =G80*G6 -> 4983.706 | H15: =H80*H6 -> 7126.6996 | I15: =I80*I6 -> 9015.275
A16: Marketing and Sales | B16: 393 | C16: 896 | D16: 997 | E16: 1680 | F16: 2725 | G16: =G81*G6 -> 3239.4089 | H16: =H81*H6 -> 3887.2907 | I16: =I81*I6 -> 5487.5587
A17: General and Administrative | B17: 314 | C17: 892 | D17: 781 | E17: 973 | F17: 1295 | G17: =G82*G6 -> 1744.2971 | H17: =H82*H6 -> 2591.5271 | I17: =I82*I6 -> 3135.7478
A18: EBIT (Operating Income) | B18: =B13-SUM(B15:B17) -> 1756 | C18: =C13-SUM(C15:C17) -> 538 | D18: =D13-SUM(D15:D17) -> 2921 | E18: =E13-SUM(E15:E17) -> 4960 | F18: =F13-SUM(F15:F17) -> 6224 | G18: =G13-SUM(G15:G17) -> 10964.153 | H18: =H13-SUM(H15:H17) -> 13605.517 | I18: =I13-SUM(I15:I17) -> 14894.802
A19: Nonoperating Income - Net | B19: -19 | C19: 7 | D19: 6 | E19: -61 | F19: -8 | G19: =G86 -> -10 | H19: =H86 -> -5 | I19: =I86 -> -11
A20: Nonoperating Interest Income | B20: 0 | C20: 14 | D20: 19 | E20: 27 | F20: 52 | G20: =G87 -> 30 | H20: =H87 -> 30 | I20: =I87 -> 38
A21: Equity in Earnings of Affiliates | B21: - | C21: 0 | D21: 0 | E21: 0 | F21: 0 | G21: =G88 -> 0 | H21: =H88 -> 0 | I21: =I88 -> 0
A22: Other Income (Expense) | B22: -19 | C22: -7 | D22: -13 | E22: -88 | F22: -60 | G22: =G89 -> 0 | H22: =H89 -> 0 | I22: =I89 -> 0
A23: Interest Expense | B23: 42 | C23: 51 | D23: 56 | E23: 23 | F23: 23 | G23: =G87 -> 30 | H23: =H87 -> 30 | I23: =I87 -> 38
A24: Gross Interest Expense | B24: 42 | C24: 51 | D24: 56 | E24: 23 | F24: 23 | G24: =G91 -> 0.4 | H24: =H91 -> 0.4 | I24: =I91 -> 0.26
A25: Interest Capitalized | B25: 0 | C25: - | D25: - | E25: 0 | F25: 0 | G25: =G92 -> 0 | H25: =H92 -> 0 | I25: =I92 -> 0
A26: Unusual Expense - Net | B26: 0 | C26: 0 | D26: 117 | E26: -34 | F26: 0 | G26: =G88 -> 0 | H26: =H88 -> 0 | I26: =I88 -> 0
A27: Fixed Assets Impairment | B27: - | C27: - | D27: - | E27: - | F27: -
A28: Financial Assets Impairment | B28: - | C28: - | D28: - | E28: - | F28: -
A29: Exceptional Provisions | B29: - | C29: 0 | D29: - | E29: 0 | F29: 0
A30: Reorganization and Restructure Expense | B30: - | C30: - | D30: 117 | E30: - | F30: -
A31: Goodwill Write Off | B31: - | C31: - | D31: - | E31: - | F31: -
A32: Legal Claim Expense | B32: - | C32: - | D32: - | E32: - | F32: -
A33: Other Intangible Assets Impairment | B33: - | C33: - | D33: - | E33: - | F33: -
A34: Unrealized Investment Loss (Gain) | B34: - | C34: - | D34: - | E34: - | F34: -
A35: Other Unusual Expense | B35: 0 | C35: 0 | D35: 0 | E35: -34 | F35: 0
A36: Pretax Income | B36: =B18+B19-B23-B26 -> 1695 | C36: =C18+C19-C23-C26 -> 494 | D36: =D18+D19-D23-D26 -> 2754 | E36: =E18+E19-E23-E26 -> 4910 | F36: =F18+F19-F23-F26 -> 6193 | G36: =G18+G19-G23-G26 -> 10924.153 | H36: =H18+H19-H23-H26 -> 13570.517 | I36: =I18+I19-I23-I26 -> 14845.802
A37: Income Taxes | B37: =B36*(B93/100) -> 695 | C37: =C36*(C93/100) -> 441 | D37: =D36*(D93/100) -> 1254 | E37: =E36*(E93/100) -> 1970 | F37: =F36*(F93/100) -> 2505.5954 | G37: =G36*(G93/100) -> 4478.9028 | H37: =H36*(H93/100) -> 5563.9121 | I37: =I36*(I93/100) -> 6086.7789
A38: Income Taxes - Current Domestic | B38: - | C38: 604 | D38: 1223 | E38: 2129 | F38: 3195
A39: Income Taxes - Current Foreign | B39: - | C39: 22 | D39: 68 | E39: 96 | F39: 123
A40: Income Taxes - Deferred Domestic | B40: - | C40: -178 | D40: -35 | E40: -254 | F40: -817
A41: Income Taxes - Deferred Foreign | B41: - | C41: -7 | D41: -2 | E41: -1 | F41: 5
A42: Income Tax Credits | B42: - | C42: - | D42: - | E42: - | F42: -
A43: Equity in Earnings of Affiliates | B43: - | C43: 0 | D43: 0 | E43: 0 | F43: 0
A44: Other After Tax Adjustments | B44: 0 | C44: -21 | D44: -9 | E44: -15 | F44: -19 | G44: -15 | H44: -10 | I44: -17
A45: Consolidated Net Income | B45: =B36-B37+B44 -> 1000 | C45: =C36-C37+C44 -> 32 | D45: =D36-D37+D44 -> 1491 | E45: =E36-E37+E44 -> 2925 | F45: =F36-F37+F44 -> 3668.4046 | G45: =G36-G37+G44 -> 6430.2504 | H45: =H36-H37+H44 -> 7996.6053 | I45: =I36-I37+I44 -> 8742.0233
A46: Minority Interest | B46: 332 | C46: 0 | D46: 0 | E46: 0 | F46: 0 | G46: 0 | H46: 0 | I46: 0
A47: Net Income | B47: =B45-B46 -> 668 | C47: =C45-C46 -> 32 | D47: =D45-D46 -> 1491 | E47: =E45-E46 -> 2925 | F47: =F45-F46 -> 3668.4046 | G47: =G45-G46 -> 6430.2504 | H47: =H45-H46 -> 7996.6053 | I47: =I45-I46 -> 8742.0233
A48: Preferred Dividends | B48: 0 | C48: 0 | D48: 0 | E48: 0 | F48: 0
A49: Net Income available to Common | B49: 668 | C49: 32 | D49: 1491 | E49: 2925 | F49: 3669
A51: EPS (recurring) | B51: 0.46352785 | C51: 0.014773777 | D51: 0.7965435 | E51: 1.089039 | F51: 1.2860147 | G51: =F51*(G90+1) -> 1.8004206 | H51: =G51*(H90+1) -> 2.5205889 | I51: =H51*(I90+1) -> 3.175942
A52: EPS (diluted) | B52: 0.443 | C52: 0.01 | D52: 0.6 | E52: 1.1 | F52: 1.29 | G52: =F52*(G91+1) -> 1.806 | H52: =G52*(H91+1) -> 2.5284 | I52: =H52*(I91+1) -> 3.185784
A53: Diluted Shares Outstanding | B53: 1508 | C53: 2166 | D53: 2517 | E53: 2664 | F53: 2853
A54: Total Shares Outstanding | B54: 1899 | C54: 2372.7052 | D54: 2546.5841 | E54: 2796.9052 | F54: 2845
A55: Earnings Persistence | B55: 45.928 | C55: 42.218 | D55: 94.246 | E55: 55.092 | F55: 83.678
A56: Dividends per Share | B56: - | C56: 0 | D56: 0 | E56: 0 | F56: 0
A57: Payout Ratio | B57: - | C57: 0 | D57: 0 | E57: 0 | F57: 0
A59: EBITDA | B59: =B18+B9 -> 2079 | C59: =C18+C9 -> 1187 | D59: =D18+D9 -> 3932 | E59: =E18+E9 -> 6203 | F59: =F18+F9 -> 8169 | G59: =G18+G9 -> 13456.006 | H59: =H18+H9 -> 16844.926 | I59: =I18+I9 -> 19206.455
A60: EBIT | B60: 1756 | C60: 538 | D60: 2921 | E60: 4960 | F60: 6225
A61: Depreciation & Amortization Expense | B61: 323 | C61: 649 | D61: 1011 | E61: 1243 | F61: 1945
A62: Supplemental
A63: Rental Expense | B63: 219 | C63: 196 | D63: 130 | E63: 125 | F63: 181
A64: Stock Option Expense | B64: 130.2 | C64: 943.2 | D64: 543.6 | E64: 1102.2 | F64: 1781.4
A65: Foreign Currency Translation Gains/Losses | B65: 29 | C65: -9 | D65: -14 | E65: -87 | F65: -66
A67: Ordinary Income | B67: - | C67: - | D67: - | E67: - | F67: -
A68: Headline EPS | B68: - | C68: - | D68: - | E68: - | F68: -
A69: Headline EPS (diluted) | B69: - | C69: - | D69: - | E69: - | F69: -
A72: Historical Data and Estimates | K72: Average | L72: Median
A73: Sales Growth | C73: =(C6/B6)-1 -> 0.37132848 | D73: =(D6/C6)-1 -> 0.54686579 | E73: =(E6/D6)-1 -> 0.5835874 | F73: =(F6/E6)-1 -> 0.43807155 | G73: 0.39 | H73: 0.3 | I73: 0.21 | K73: =AVERAGE(C73:F73) -> 0.48496331 | L73: =MEDIAN(C73:F73) -> 0.49246867
A75: Operating Expenses:
A76: SG&A as % of Revenue | B76: =B14/B$6 -> 0.29506871 | C76: =C14/C$6 -> 0.6262527 | D76: =D14/D$6 -> 0.40561484 | E76: =E14/E$6 -> 0.42668057 | F76: =F14/F$6 -> 0.49288782 | G76: 0.4 | H76: 0.42 | I76: 0.4 | K76: =AVERAGE(B76:F76) -> 0.44930093 | L76: =MEDIAN(B76:F76) -> 0.42668057
A77: D&A as % of Revenue | B77: =B9/B6 -> 0.087038534 | C77: =C9/C6 -> 0.12752997 | D77: =D9/D6 -> 0.12842988 | E77: =E9/E6 -> 0.099711215 | F77: =F9/F6 -> 0.10849557 | G77: 0.1 | H77: 0.1 | I77: 0.11 | K77: =AVERAGE(B77:F77) -> 0.11024103 | L77: =MEDIAN(B77:F77) -> 0.10849557
A78: COGS as % of Revenue | B78: =B8/B6 -> 0.14470493 | C78: =C8/C6 -> 0.14049912 | D78: =D8/D6 -> 0.094893293 | E78: =E8/E6 -> 0.075725975 | F78: =F8/F6 -> 0.051430803 | G78: 0.06 | H78: 0.06 | I78: 0.06 | K78: =AVERAGE(B78:F78) -> 0.10145082 | L78: =MEDIAN(B78:F78) -> 0.094893293
A79: Cost of Revenue as a % of Revenue | B79: =B77+B78 -> 0.23174347 | C79: =C77+C78 -> 0.26802908 | D79: =D77+D78 -> 0.22332317 | E79: =E77+E78 -> 0.17543719 | F79: =F77+F78 -> 0.15992637 | G79: =G77+G78 -> 0.16 | H79: =H77+H78 -> 0.16 | I79: =I77+I78 -> 0.17 | K79: =AVERAGE(B79:F79) -> 0.21169186 | L79: =MEDIAN(B79:F79) -> 0.22332317
A80: Research & Development as a % of Revenue | B80: =B15/B6 -> 0.10455403 | C80: =C15/C6 -> 0.27490666 | D80: =D15/D6 -> 0.17975102 | E80: =E15/E6 -> 0.2138617 | F80: =F15/F6 -> 0.26864506 | G80: 0.2 | H80: 0.22 | I80: 0.23 | K80: =AVERAGE(B80:F80) -> 0.20834369 | L80: =MEDIAN(B80:F80) -> 0.2138617
A81: Marketing and Sales as a % of Revenue | B81: =B16/B6 -> 0.10590137 | C81: =C16/C6 -> 0.17606602 | D81: =D16/D6 -> 0.12665142 | E81: =E16/E6 -> 0.13476657 | F81: =F16/F6 -> 0.15200536 | G81: 0.13 | H81: 0.12 | I81: 0.14 | K81: =AVERAGE(B81:F81) -> 0.13907815 | L81: =MEDIAN(B81:F81) -> 0.13476657
A82: General and Administrative as a % of Revenue | B82: =B17/B6 -> 0.084613312 | C82: =C17/C6 -> 0.17528002 | D82: =D17/D6 -> 0.099212398 | E82: =E17/E6 -> 0.078052302 | F82: =F17/F6 -> 0.072237407 | G82: 0.07 | H82: 0.08 | I82: 0.08 | K82: =AVERAGE(B82:F82) -> 0.10187909 | L82: =MEDIAN(B82:F82) -> 0.084613312
A83: Total Operating Expenses as % of Revenue | B83: =SUM(B79:B82) -> 0.52681218 | C83: =SUM(C79:C82) -> 0.89428178 | D83: =SUM(D79:D82) -> 0.62893801 | E83: =SUM(E79:E82) -> 0.60211776 | F83: =SUM(F79:F82) -> 0.65281419 | G83: =SUM(G79:G82) -> 0.56 | H83: =SUM(H79:H82) -> 0.58 | I83: =SUM(I79:I82) -> 0.62 | K83: =AVERAGE(B83:F83) -> 0.66099278 | L83: =MEDIAN(B83:F83) -> 0.62893801
A84: EBIT Margin | B84: =B18/B6 -> 0.47318782 | C84: =C18/C6 -> 0.10571822 | D84: =D18/D6 -> 0.37106199 | E84: =E18/E6 -> 0.39788224 | F84: =F18/F6 -> 0.34718581 | G84: =G18/G6 -> 0.44 | H84: =H18/H6 -> 0.42 | I84: =I18/I6 -> 0.38 | K84: =AVERAGE(B84:F84) -> 0.33900722 | L84: =MEDIAN(B84:F84) -> 0.37106199
A85: Other Income (Expenses):
A86: =CONCATENATE(A19," as a % of Revenue") -> Nonoperating Income - Net as a % of Revenue | B86: =B19 -> -19 | C86: =C19 -> 7 | D86: =D19 -> 6 | E86: =E19 -> -61 | F86: =F19 -> -8 | G86: -10 | H86: -5 | I86: -11 | K86: =AVERAGE(B86:F86) -> -15 | L86: =MEDIAN(B86:F86) -> -8
A87: =CONCATENATE(A20," as a % of Revenue") -> Nonoperating Interest Income as a % of Revenue | B87: =B23 -> 42 | C87: =C23 -> 51 | D87: =D23 -> 56 | E87: =E23 -> 23 | F87: =F23 -> 23 | G87: 30 | H87: 30 | I87: 38 | K87: =AVERAGE(B87:F87) -> 39 | L87: =MEDIAN(B87:F87) -> 42
A88: =CONCATENATE(A21," as a % of Revenue") -> Equity in Earnings of Affiliates as a % of Revenue | B88: =B26 -> 0 | C88: =C26 -> 0 | D88: =D26 -> 117 | E88: =E26 -> -34 | F88: =F26 -> 0 | G88: 0 | H88: 0 | I88: 0 | K88: =AVERAGE(B88:F88) -> 16.6 | L88: =MEDIAN(B88:F88) -> 0
A90: EPS (recurring) change | C90: =C51/B51-1 -> -0.96812753 | D90: =D51/C51-1 -> 52.916038 | E90: =E51/D51-1 -> 0.36720598 | F90: =F51/E51-1 -> 0.18087109 | G90: 0.4 | H90: 0.4 | I90: 0.26 | K90: =AVERAGE(C90:F90) -> 13.123997 | L90: =MEDIAN(C90:F90) -> 0.27403853
A91: EPS (diluted) change | C91: =C52/B52-1 -> -0.97742664 | D91: =D52/C52-1 -> 59 | E91: =E52/D52-1 -> 0.83333333 | F91: =F52/E52-1 -> 0.17272727 | G91: 0.4 | H91: 0.4 | I91: 0.26 | K91: =AVERAGE(C91:F91) -> 14.757158 | L91: =MEDIAN(C91:F91) -> 0.5030303
A93: Tax Rate | B93: 41.00295 | C93: 89.271255 | D93: 45.533769 | E93: 40.1222 | F93: 40.458508 | G93: 41 | H93: 41 | I93: 41

Sheet Valuation
A1: Facebook
A2: Dollars in Millions, except per share
A3: Current Share Price | E3: 112.26
D5: PE | E5: EPS
C6: 2016 | D6: =$E$3/E6 -> 62.159468 | E6: ='FB Income Statement '!G52 -> 1.806
C7: 2017 | D7: =$E$3/E7 -> 44.39962 | E7: ='FB Income Statement '!H52 -> 2.5284
C8: =C7+1 -> 2018 | D8: =$E$3/E8 -> 35.237794 | E8: ='FB Income Statement '!I52 -> 3.185784
C14: PEx | E14: 55
C15: 2017 | E15: =E7 -> 2.5284
C16: PEx Value | E16: =E14*E15 -> 139.062
C17: DCF Value
C18: Average | E18: =AVERAGE(E16:E17) -> 139.062
B19: Upside (Downside) | C19: % | E19: =(E18/E3)-1 -> 0.23874933

Sheet DCF
A1: DCF Analysis
A2: Dollars in Millions, except per share
H3: Proj 2016 | I3: Proj 2017 | J3: Proj 2018
A4: EBITDA | H4: ='FB Income Statement '!G59 -> 13456.006 | I4: ='FB Income Statement '!H59 -> 16844.926 | J4: ='FB Income Statement '!I59 -> 19206.455
A5: Less: Depreciation & Amortization | H5: =-'FB Income Statement '!G9 -> -2491.853 | I5: =-'FB Income Statement '!H9 -> -3239.4089 | J5: =-'FB Income Statement '!I9 -> -4311.6532
A6: EBIT | H6: =SUM(H4:H5) -> 10964.153 | I6: =SUM(I4:I5) -> 13605.517 | J6: =SUM(J4:J5) -> 14894.802
A7: Less: Taxes @ | C7: 0.4 | H7: =-H6*$C7 -> -4385.6613 | I7: =-I6*$C7 -> -5442.207 | J7: =-J6*$C7 -> -5957.9208
A8: Tax-effected EBIT | H8: =SUM(H6:H7) -> 6578.4919 | I8: =SUM(I6:I7) -> 8163.3104 | J8: =SUM(J6:J7) -> 8936.8813
A9: Free Cash Flow to Firm (adj for 1Q) | H9: ='USE OF CASH FCST DATA'!K8 -> 6683.6 | I9: ='USE OF CASH FCST DATA'!L8 -> 8688.68 | J9: ='USE OF CASH FCST DATA'!M8 -> 11295.284
E11: Perpetuity (Normalized) | K11: EBITDA Exit Multiple
E13: Weighted average cost of capital: | K13: Weighted average cost of capital:
E14: Net present value of free cash flow | K14: Net present value of free cash flow
E16: ="Normalized FCFF post "&N3 -> Normalized FCFF post | K16: Exit multiple post 2020
E17: Terminal value | K17: Terminal value
E18: Present value of the terminal value | K18: Present value of the terminal value
E20: Enterprise Value | K20: Enterprise Value
E21: - Total Debt | K21: =E21 -> - Total Debt
E22: - Minority Interest | K22: =E22 -> - Minority Interest
E23: - Preferred Equity | K23: =E23 -> - Preferred Equity
E24: + Cash | K24: =E24 -> + Cash
E25: Equity Value | K25: Equity Value
E27: Diluted shares: | K27: Diluted shares:
E29: Equity Value Per Share | K29: Equity Value Per Share

Sheet IS FCST DATA
A1: Income Statement - As Reported
B2: 31 Dec '11 (Ann) | C2: 31 Dec '12 (Ann) | D2: 31 Dec '13 (Ann) | E2: 31 Dec '14 (Ann) | F2: 31 Dec '15 (Ann)
B3: 31 Jan '14 (1Y) | C3: 29 Jan '15 (1Y) | D3: 28 Jan '16 (1Y) | E3: 28 Jan '16 (1Y) | F3: 28 Jan '16 (1Y)
B4: USD | C4: USD | D4: USD | E4: USD | F4: USD
B5: 10-K (R) | C5: 10-K (R) | D5: 10-K (R) | E5: 10-K (R) | F5: 10-K
A6: Revenue | B6: 3711 | C6: 5089 | D6: 7872 | E6: 12466 | F6: 17928
A7: Total costs and expenses | B7: -1955 | C7: -4551 | D7: -5068 | E7: -7472 | F7: -11703
A8: Cost of revenue | B8: -860 | C8: -1364 | D8: -1875 | E8: -2153 | F8: -2867
A9: Research and development | B9: -388 | C9: -1399 | D9: -1415 | E9: -2666 | F9: -4816
A10: Marketing and sales | B10: -393 | C10: -896 | D10: -997 | E10: -1680 | F10: -2725
A11: General and administrative | B11: -314 | C11: -892 | D11: -781 | E11: -973 | F11: -1295
A12: Income / loss from operations | B12: 1756 | C12: 538 | D12: 2804 | E12: 4994 | F12: 6225
A13: Interest and other income / expense, net | B13: -61 | C13: -44 | D13: -50 | E13: -84 | F13: -31
A14: Interest expense | B14: -42 | C14: -- | D14: -- | E14: -- | F14: --
A15: Other income / expense, net | B15: -19 | C15: -- | D15: -- | E15: -- | F15: --
A16: Income / loss before provision for / benefit from income taxes | B16: 1695 | C16: 494 | D16: 2754 | E16: 4910 | F16: 6194
A17: Provision for / benefit from income taxes | B17: -695 | C17: -441 | D17: -1254 | E17: -1970 | F17: -2506
A18: Net income / loss | B18: 1000 | C18: 53 | D18: 1500 | E18: 2940 | F18: 3688
A19: Net income attributable to participating securities | B19: -332 | C19: -21 | D19: -9 | E19: -15 | F19: -19
A20: Net income / loss attributable to Class A and Class B common stockholders | B20: 668 | C20: 32 | D20: 1491 | E20: 2925 | F20: 3669

Sheet CF FCST DATA
A1: Cash Flow - As Reported
B2: 31 Dec '11 (Ann) | C2: 31 Dec '12 (Ann) | D2: 31 Dec '13 (Ann) | E2: 31 Dec '14 (Ann) | F2: 31 Dec '15 (Ann)
B3: 31 Jan '14 (1Y) | C3: 29 Jan '15 (1Y) | D3: 28 Jan '16 (1Y) | E3: 28 Jan '16 (1Y) | F3: 28 Jan '16 (1Y)
B4: USD | C4: USD | D4: USD | E4: USD | F4: USD
B5: 10-K (R) | C5: 10-K (R) | D5: 10-K (R) | E5: 10-K (R) | F5: 10-K
A6: Net cash provided by operating activities | B6: 1549 | C6: 1612 | D6: 4222 | E6: 5457 | F6: 8599
A7: Net income / loss | B7: 1000 | C7: 53 | D7: 1500 | E7: 2940 | F7: 3688
A8: Adjustments to reconcile net income / loss to net cash provided by operating activities | B8: 514 | C8: 2058 | D8: 2046 | E8: 2779 | F8: 4127
A9: Depreciation and amortization | B9: 323 | C9: 649 | D9: 1011 | E9: 1243 | F9: 1945
A10: Loss on disposal or write-off of equipment | B10: 4 | C10: -- | D10: -- | E10: -- | F10: --
A11: Share-based compensation | B11: 217 | C11: 1572 | D11: 906 | E11: 1786 | F11: 2960
A12: Deferred income taxes | B12: -30 | C12: -186 | D12: -37 | E12: -210 | F12: -795
A13: Tax benefit from share-based award activity | B13: 433 | C13: 1033 | D13: 602 | E13: 1853 | F13: 1721
A14: Excess tax benefit from share-based award activity | B14: -433 | C14: -1033 | D14: -609 | E14: -1869 | F14: -1721
A15: Other | B15: 0 | C15: 23 | D15: 173 | E15: -24 | F15: 17
A16: Lease abandonment | B16: 0 | C16: 8 | D16: 117 | E16: -31 | F16: 0
A17: Other excluding lease abandonment | B17: -- | C17: 15 | D17: 56 | E17: 7 | F17: 17
A18: Changes in assets and liabilities | B18: 35 | C18: -499 | D18: 676 | E18: -262 | F18: 784
A19: Accounts receivable | B19: -174 | C19: -170 | D19: -378 | E19: -610 | F19: -973
A20: Prepaid expenses and other current assets | B20: -24 | C20: -465 | D20: 355 | E20: -123 | F20: -144
A21: Income tax refundable | B21: 0 | C21: -- | D21: -- | E21: -- | F21: --
A22: Prepaid expenses and other current assets excluding income tax refundable | B22: -24 | C22: -- | D22: -- | E22: -- | F22: --
A23: Other assets | B23: -5 | C23: 2 | D23: -142 | E23: -216 | F23: -3
A24: Accounts payable | B24: 6 | C24: 1 | D24: 26 | E24: 31 | F24: 18
A25: Partners payable | B25: 96 | C25: -2 | D25: 12 | E25: -28 | F25: 17
A26: Accrued expenses and other current liabilities | B26: 37 | C26: 152 | D26: -38 | E26: 328 | F26: 513
A27: Deferred revenue and deposits | B27: 49 | C27: -60 | D27: 8 | E27: 10 | F27: -9
A28: Other liabilities | B28: 50 | C28: 43 | D28: 833 | E28: 346 | F28: 1365
A29: Net cash used in / provided by investing activities | B29: -3023 | C29: -7024 | D29: -2624 | E29: -5913 | F29: -9434
A30: Purchases of property and equipment | B30: -606 | C30: -1235 | D30: -1362 | E30: -1831 | F30: -2523
A31: Purchases of marketable securities | B31: -3025 | C31: -10307 | D31: -7433 | E31: -9104 | F31: -15938
A32: Sales of marketable securities | B32: 113 | C32: 2100 | D32: 2988 | E32: 8438 | F32: 6928
A33: Maturities of marketable securities | B33: 516 | C33: 3333 | D33: 3563 | E33: 1909 | F33: 2310
A34: Acquisitions of businesses, net of cash acquired, and purchases of intangible assets | B34: -24 | C34: -911 | D34: -368 | E34: -4975 | F34: -313
A35: Other investing activities, net | B35: 3 | C35: -4 | D35: -12 | E35: -350 | F35: 102
A36: Investments in non-marketable equity securities | B36: -3 | C36: -- | D36: -- | E36: -- | F36: --
A37: Change in restricted cash and deposits | B37: 6 | C37: -2 | D37: -11 | E37: -348 | F37: 102
A38: Other investing activities, net excluding investments in non-marketable equity securities and change in restricted cash and deposits | B38: -- | C38: -2 | D38: -1 | E38: -2 | F38: 0
A39: Net cash used in / provided by financing activities | B39: 1198 | C39: 6283 | D39: -667 | E39: 1571 | F39: 1582
A40: Net proceeds from issuance of convertible preferred stock | B40: -- | C40: -- | D40: -- | E40: -- | F40: --
A41: Net proceeds from issuance of common stock | B41: 998 | C41: 6760 | D41: 1478 | E41: 0 | F41: 0
A42: Taxes paid related to net share settlement | B42: 0 | C42: -2862 | D42: -889 | E42: -73 | F42: -20
A43: Proceeds from exercise of stock options | B43: 28 | C43: 17 | D43: 26 | E43: 18 | F43: 0
A44: Proceeds from / repayments of long-term debt | B44: -250 | C44: 1496 | D44: -1500 | E44: 0 | F44: 0
A45: Proceeds from long-term debt, net of issuance cost | B45: 0 | C45: 1496 | D45: -- | E45: -- | F45: --
A46: Repayment of long-term debt | B46: -250 | C46: 0 | D46: -1500 | E46: 0 | F46: 0
A47: Proceeds from sale and lease-back transactions | B47: 170 | C47: 205 | D47: -- | E47: -- | F47: --
A48: Principal payments on capital lease obligations | B48: -181 | C48: -366 | D48: -391 | E48: -243 | F48: -119
A49: Excess tax benefit from share-based award activity | B49: 433 | C49: 1033 | D49: 609 | E49: 1869 | F49: 1721
A50: Effect of exchange rate changes on cash and cash equivalents | B50: 3 | C50: 1 | D50: 8 | E50: -123 | F50: -155
A51: Net increase / decrease in cash and cash equivalents | B51: -273 | C51: 872 | D51: 939 | E51: 992 | F51: 592
A52: Cash and cash equivalents at beginning of period | B52: 1785 | C52: 1512 | D52: 2384 | E52: 3323 | F52: 4315
A53: Cash and cash equivalents at end of period | B53: 1512 | C53: 2384 | D53: 3323 | E53: 4315 | F53: 4907
A54: Cash paid / received during the period for | B54: -- | C54: -- | D54: -- | E54: -- | F54: --
A55: Interest | B55: -28 | C55: -38 | D55: -38 | E55: -14 | F55: -10
A56: Income taxes, net | B56: -197 | C56: 315 | D56: 339 | E56: -178 | F56: -270
A57: Income taxes paid | B57: -197 | C57: 184 | D57: -82 | E57: -184 | F57: -273
A58: Income taxes received | B58: 0 | C58: 131 | D58: 421 | E58: 6 | F58: 3
A59: Non-cash investing and financing activities | B59: -- | C59: -- | D59: -- | E59: -- | F59: --
A60: Net change in accounts payable, accrued expenses and other current liabilities, and other liabilities related to property and equipment additions | B60: 135 | C60: -40 | D60: 53 | E60: 91 | F60: 88
A61: Property and equipment acquired under capital leases | B61: -473 | C61: -340 | D61: -11 | E61: 0 | F61: 0
A62: Fair value of shares issued related to acquisitions of businesses | B62: 58 | C62: 274 | D62: 77 | E62: 14344 | F62: 0
A63: Promissory note payable issued in connection with an acquisition | B63: -- | C63: -- | D63: 0 | E63: 0 | F63: 198

Sheet USE OF CASH FCST DATA
A1: Facebook, Inc. Class A
A2: Use of Cash
B3: Dec '07 | C3: Dec '08 | D3: Dec '09 | E3: Dec '10 | F3: Dec '11 | G3: Dec '12 | H3: Dec '13 | I3: Dec '14 | J3: Dec '15
C4: 366 Days | D4: 365 Days | E4: 365 Days | F4: 365 Days | G4: 366 Days | H4: 365 Days | I4: 365 Days | J4: 365 Days
A5: Total Cash
A6: Previous Balance Sheet Amt + Cash Inflows | B6: 11 | C6: 306 | D6: 691 | E6: 1267 | F6: 1982 | G6: 5196 | H6: 12504 | I6: 12830 | J6: 12088
A7: Cash Flow
A8: Free Cash Flow | B8: 0 | C8: 0 | D8: 122 | E8: 405 | F8: 943 | G8: 377 | H8: 2860 | I8: 3626 | J8: 6076 | K8: =J8*(1+K38) -> 6683.6 | L8: =K8*(1+L38) -> 8688.68 | M8: =L8*(1+M38) -> 11295.284
A9: Net Operating Cash Flow | B9: 0 | C9: 0 | D9: 155 | E9: 698 | F9: 1549 | G9: 1612 | H9: 4222 | I9: 5457 | J9: 8599
A10: Capital Expenditures | B10: 0 | C10: 0 | D10: -33 | E10: -293 | F10: -606 | G10: -1235 | H10: -1362 | I10: -1831 | J10: -2523 | K10: =J10*(K39+1) -> -3910.65 | L10: =K10*(L39+1) -> -5122.9515 | M10: =L10*(M39+1) -> -5891.3942
A11: Interest Expense | B11: 11 | C11: 1 | D11: 10 | E11: 22 | F11: 42 | G11: 51 | H11: 56 | I11: 23 | J11: 23
A12: Preferred Dividends | B12: 0 | C12: 0 | D12: 0 | E12: 0 | F12: 0 | G12: 0 | H12: 0 | I12: 0 | J12: 0
A13: Mergers & Acquisitions | B13: 0 | C13: 0 | D13: 3 | E13: -22 | F13: -24 | G13: -911 | H13: -368 | I13: -4975 | J13: -313
A14: Business Divestitures | B14: 0 | C14: 0 | D14: 3 | E14: 0 | F14: 0 | G14: 0 | H14: 0 | I14: 0 | J14: 0
A15: Business Acquisitions | B15: 0 | C15: 0 | D15: 0 | E15: -22 | F15: -24 | G15: -911 | H15: -368 | I15: -4975 | J15: -313
A16: Purchase/Sale of Investments | B16: 0 | C16: 0 | D16: 0 | E16: 0 | F16: -2399 | G16: -4876 | H16: -883 | I16: 1243 | J16: -6700
A17: Other Funds | B17: 0 | C17: 0 | D17: 50 | E17: 106 | F17: 609 | G17: -1626 | H17: -291 | I17: 1446 | J17: 1803
A18: Cash Increase/Decrease | B18: 11 | C18: 1 | D18: 185 | E18: 511 | F18: -829 | G18: -6985 | H18: 1374 | I18: 1363 | J18: 889
A19: Debt
A20: Debt Issuance | B20: 0 | C20: 0 | D20: 0 | E20: 250 | F20: 0 | G20: 1496 | H20: 0 | I20: 0 | J20: 0
A21: Interest Expense | B21: -11 | C21: -1 | D21: -10 | E21: -22 | F21: -42 | G21: -51 | H21: -56 | I21: -23 | J21: -23
A22: Repayment of Debt | B22: 0 | C22: 0 | D22: -48 | E22: -90 | F22: -431 | G22: -366 | H22: -1891 | I22: -243 | J22: -119
A23: Cash Received (Paid) from Debt Activity | B23: -11 | C23: -1 | D23: -58 | E23: 138 | F23: -473 | G23: 1079 | H23: -1947 | I23: -266 | J23: -142
A24: Dividends
A25: Common Dividends | B25: 0 | C25: 0 | D25: 0 | E25: 0 | F25: 0 | G25: 0 | H25: 0 | I25: 0 | J25: 0
A26: Preferred Dividends | B26: 0 | C26: 0 | D26: 0 | E26: 0 | F26: 0 | G26: 0 | H26: 0 | I26: 0 | J26: 0
A27: Dividends Paid | B27: 0 | C27: 0 | D27: 0 | E27: 0 | F27: 0 | G27: 0 | H27: 0 | I27: 0 | J27: 0
A28: Share Issued/Repurchased
A29: Equity Issuance/Option Exercise Proceeds | B29: 0 | C29: 0 | D29: 209 | E29: 506 | F29: 1026 | G29: 6777 | H29: 1504 | I29: 18 | J29: 0
A30: Repurchase of Common/Preferred Stock | B30: 0 | C30: 0 | D30: 0 | E30: 0 | F30: 0 | G30: 0 | H30: 0 | I30: 0 | J30: 0
A31: Cash Received (Paid) from Change in Equity | B31: 0 | C31: 0 | D31: 209 | E31: 506 | F31: 1026 | G31: 6777 | H31: 1504 | I31: 18 | J31: 0
A32: Cash
A33: Exchange Rate Effect | B33: 0 | C33: 0 | D33: 0 | E33: -3 | F33: 3 | G33: 1 | H33: 8 | I33: -123 | J33: -155
A34: Net Change in Cash (FX Adjusted) | B34: 0 | C34: 0 | D34: 336 | E34: 1152 | F34: -273 | G34: 872 | H34: 939 | I34: 992 | J34: 592
A35: Cash on Balance Sheet | B35: 305 | C35: 297 | D35: 0 | E35: 1785 | F35: 3908 | G35: 9626 | H35: 11449 | I35: 11199 | J35: 18434
A38: FCF Growth | G38: =(G8/F8)- 1 -> -0.60021209 | H38: =(H8/G8)- 1 -> 6.5862069 | I38: =(I8/H8)- 1 -> 0.26783217 | J38: =(J8/I8)- 1 -> 0.67567568 | K38: 0.1 | L38: 0.3 | M38: 0.3 | O38: =AVERAGE(G38:J38) -> 1.7323757 | P38: =MEDIAN(G38:J38) -> 0.47175392
A39: Capex Growth | G39: =(G9/F9)-1 -> 0.040671401 | H39: =(H9/G9)-1 -> 1.6191067 | I39: =(I9/H9)-1 -> 0.2925154 | J39: =(J9/I9)-1 -> 0.57577423 | K39: 0.55 | L39: 0.31 | M39: 0.15 | O39: =AVERAGE(G39:J39) -> 0.63201693 | P39: =MEDIAN(G39:J39) -> 0.43414482

Sheet Ratio Analysis
A1: Facebook, Inc. Class A
A2: FB 30303M102 B7TL820 NASDAQ Common stock
A3: Ratios - Annual
A4: Source : FactSet Fundamentals
A5: Year/Year growth
B6: 5 Yr AVG | C6: Dec '11 | D6: Dec '12 | E6: Dec '13 | F6: Dec '14 | G6: Dec '15
C7: 365 DAYS | D7: 366 DAYS | E7: 365 DAYS | F7: 365 DAYS | G7: 365 DAYS
A8: Profitability (%)
A9: Gross Margin | B9: 78.830993 | C9: 76.825653 | D9: 73.197092 | E9: 77.667683 | F9: 82.456281 | G9: 84.008255
A10: SG&A to Sales | B10: 44.929543 | C10: 29.506871 | D10: 62.62527 | E10: 40.561484 | F10: 42.668057 | G10: 49.286033
A11: Operating Margin | B11: 33.901449 | C11: 47.318782 | D11: 10.571822 | E11: 37.106199 | F11: 39.788224 | G11: 34.722222
A12: Pretax Margin | B12: 32.860686 | C12: 45.67502 | D12: 9.7072116 | E12: 34.984756 | F12: 39.387133 | G12: 34.549308
A13: Net Margin | B13: 16.299782 | C13: 18.000539 | D13: 0.62880723 | E13: 18.940549 | F13: 23.463822 | G13: 20.465194
A14: Return on Assets | B14: 8.3863542 | C14: 14.333226 | D14: 0.29859102 | E14: 9.0369113 | F14: 10.072487 | G14: 8.1905549
A15: Return on Equity | B15: 10.147924 | C15: 18.920833 | D15: 0.38429206 | E15: 10.953168 | F15: 11.344684 | G15: 9.1366387
A16: Return on Common Equity | B16: 10.949108 | C16: 22.912022 | D16: 0.39902737 | E16: 10.953168 | F16: 11.344684 | G16: 9.1366387
A17: Return on Total Capital | B17: 9.3565263 | C17: 16.270856 | D17: 0.32508762 | E17: 9.9211498 | F17: 11.190818 | G17: 9.0747199
A18: Return on Invested Capital | B18: 9.5819775 | C18: 17.071301 | D18: 0.3360815 | E18: 10.124605 | F18: 11.2669 | G18: 9.1110007
A19: Cash Flow Return on Invested Capital | B19: 25.511772 | C19: 39.585995 | D19: 16.930106 | E19: 28.669405 | F19: 21.019992 | G19: 21.353365
A21: Valuation (x)
A22: Price/Sales | C22: -- | D22: 11.32998 | E22: 17.473518 | F22: 16.672973 | G22: 16.655231
A23: Price/Earnings | C23: -- | D23: 2661.97 | E23: 91.081667 | F23: 70.927273 | G23: 81.131783
A24: Price/Book Value | C24: -- | D24: 5.3730931 | E24: 8.9960163 | F24: 6.0453955 | G24: 6.7338551
A25: Price/Tangible Book Value | C25: -- | D25: 6.0924762 | E25: 10.122801 | F25: 15.382387 | G25: 12.976453
A26: Price/Cash Flow | C26: -- | D26: 35.768158 | E26: 32.579709 | F26: 38.087828 | G26: 34.724384
A27: Price/Free Cash Flow | C27: -- | D27: 152.93971 | E27: 48.094942 | F27: 57.320816 | G27: 49.143348
A28: Enterprise Value/EBIT | C28: -- | D28: 103.88605 | E28: 43.887458 | F28: 41.783982 | G28: 44.921883
A29: Enterprise Value/EBITDA | C29: -- | D29: 47.085674 | E29: 32.603069 | F29: 33.411019 | G29: 34.227506
A30: Enterprise Value/Sales | C30: -- | D30: 10.982648 | E30: 16.284968 | F30: 16.625104 | G30: 15.597876
A31: Total Debt/Enterprise Value | C31: -- | D31: 0.042153707 | E31: 0.0037130856 | F31: 0.0011242539 | G31: 0.0011264534
A33: Per Share
A34: Sales per Share | B34: 3.7802482 | C34: 2.4608753 | D34: 2.3494922 | E34: 3.1275328 | F34: 4.6794294 | G34: 6.2839117
A35: EBIT (Operating Income) per Share | B35: 1.3234249 | C35: 1.1644562 | D35: 0.24838412 | E35: 1.1605085 | F35: 1.8618619 | G35: 2.1819138
A36: EPS (recurring) | B36: 0.72997979 | C36: 0.46352785 | D36: 0.014773777 | E36: 0.7965435 | F36: 1.089039 | G36: 1.2860147
A37: EPS (diluted) | B37: 0.6886 | C37: 0.443 | D37: 0.01 | E37: 0.6 | F37: 1.1 | G37: 1.29
A38: Book Value per Share | B38: 8.346606 | C38: 2.25592 | D38: 4.95426 | E38: 6.0748 | F38: 12.90569 | G38: 15.54236
A39: Tangible Book Value per Share | B39: 5.0151815 | C39: 2.1706161 | D39: 4.3692744 | E39: 5.3986044 | F39: 5.0720346 | G39: 8.0653779
A40: Cash Flow per Share | B40: 1.702251 | C40: 1.0271883 | D40: 0.74422899 | E40: 1.6773937 | F40: 2.0484234 | G40: 3.0140203
A41: Free Cash Flow per Share | B41: 1.0852915 | C41: 0.62533156 | D41: 0.17405355 | E41: 1.1362733 | F41: 1.3611111 | G41: 2.129688
A42: Diluted Shares Outstanding | B42: 2341.6 | C42: 1508 | D42: 2166 | E42: 2517 | F42: 2664 | G42: 2853
A43: Total Shares Outstanding | B43: 2492.0389 | C43: 1899 | D43: 2372.7052 | E43: 2546.5841 | F43: 2796.9052 | G43: 2845
A45: Asset Turnover Analysis (x)
A46: Cash & ST Investments | B46: 1.0227269 | C46: 1.3037063 | D46: 0.75203192 | E46: 0.74704626 | F46: 1.1008478 | G46: 1.2100024
A47: Receivables | B47: 7.5999809 | C47: 8.0673913 | D47: 5.927781 | E47: 6.7570815 | F47: 8.7850599 | G47: 8.4625915
A48: Current Assets | B48: 0.86384383 | C48: 1.0835036 | D48: 0.64129544 | E48: 0.64691622 | F48: 0.93238594 | G48: 1.0151181
A49: Fixed Assets | B49: 3.3190149 | C49: 3.6222548 | D49: 2.6326953 | E49: 2.9857766 | F49: 3.6402395 | G49: 3.7141081
A50: Total Assets | B50: 0.5155471 | C50: 0.7962665 | D50: 0.47485304 | E50: 0.47711983 | F50: 0.42927736 | G50: 0.40021877
A52: DuPont Analysis
A53: Asset Turnover (x) | B53: 0.5155471 | C53: 0.7962665 | D53: 0.47485304 | E53: 0.47711983 | F53: 0.42927736 | G53: 0.40021877
A54: x Pretax Margin (%) | B54: 32.860686 | C54: 45.67502 | D54: 9.7072116 | E54: 34.984756 | F54: 39.387133 | G54: 34.549308
A55: = Pretax Return on Assets (%) | B55: 17.681239 | C55: 36.369488 | D55: 4.6094989 | E55: 16.691921 | F55: 16.908005 | G55: 13.827282
A56: x Tax Rate Complement (1-Tax Rate) | B56: 48.722264 | C56: 58.99705 | D56: 10.728745 | E56: 54.466231 | F56: 59.8778 | G56: 59.541492
A57: = Return on Assets (%) | B57: 8.3863542 | C57: 14.333226 | D57: 0.29859102 | E57: 9.0369113 | F57: 10.072487 | G57: 8.1905549
A58: x Equity Multiplier (Assets/Equity) | B58: 1.2121894 | C58: 1.320068 | D58: 1.2870181 | E58: 1.2120478 | F58: 1.1263042 | G58: 1.1155091
A59: = Return on Equity (%) | B59: 10.147924 | C59: 18.920833 | D59: 0.38429206 | E59: 10.953168 | F59: 11.344684 | G59: 9.1366387
A60: x Earnings Retention (1-Payout) | C60: -- | D60: 100 | E60: 100 | F60: 100 | G60: 100
A61: = Reinvestment Rate (%) | B61: 10.147924 | C61: 18.920833 | D61: 0.38429206 | E61: 10.953168 | F61: 11.344684 | G61: 9.1366387
A62: Note: EBIT Return on Assets (%) | B62: 18.275838 | C62: 37.678361 | D62: 5.0200616 | E62: 17.704103 | F62: 17.080184 | G62: 13.896485
A63: Note: Interest as % Assets | B63: 0.28356179 | C63: 0.66340231 | D63: 0.33768126 | E63: 0.31293657 | F63: 0.057236711 | G63: 0.046552108
A65: Operating Efficiency
A66: Revenue/Employee | C66: -- | D66: 1.1017536 | E66: 1.2422282 | F66: 1.3551473 | G66: 1.4126546
A67: Net Income/Employee | C67: -- | D67: 0.0069279065 | E67: 0.23528484 | F67: 0.31796934 | G67: 0.28910251
A68: Assets/Employee | C68: -- | D68: 3.2697554 | E68: 2.8238914 | F68: 4.3683009 | G68: 3.8930738
A69: Receivables Turnover (x) | B69: 7.5999809 | C69: 8.0673913 | D69: 5.927781 | E69: 6.7570815 | F69: 8.7850599 | G69: 8.4625915
A70: Payables Turnover (x) | C70: -- | D70: -- | E70: 10.5586 | F70: 6.7709 | G70: 7.2491
A71: Asset Turnover (x) | B71: 0.5155471 | C71: 0.7962665 | D71: 0.47485304 | E71: 0.47711983 | F71: 0.42927736 | G71: 0.40021877
A72: Working Capital Turnover (x) | B72: 0.81684457 | C72: 1.0016194 | D72: 0.49818894 | E72: 0.65764411 | F72: 1.017965 | G72: 0.90880519
A74: Operating Cycle (Days)
A75: Days of Inventory on Hand | C75: -- | D75: -- | E75: -- | F75: -- | G75: --
A76: + Days of Sales Outstanding | B76: 49.102911 | C76: 45.24387 | D76: 61.574474 | E76: 54.017403 | F76: 41.54781 | G76: 43.130996
A77: = Operating Cycle | C77: -- | D77: -- | E77: -- | F77: -- | G77: --
A78: - Days of Payables Outstanding | C78: -- | D78: -- | E78: 34.568977 | F78: 53.907162 | G78: 50.351078
A80: Liquidity
A81: Current Ratio | B81: 9.7121302 | C81: 5.1212458 | D81: 10.710076 | E81: 11.881818 | F81: 9.5997191 | G81: 11.247792
A82: Quick Ratio | C82: -- | D82: 10.710076 | E82: 11.881818 | F82: 9.5997191 | G82: 11.247792
A83: Cash Ratio | B83: 8.2691988 | C83: 4.3470523 | D83: 9.1501901 | E83: 10.408182 | F83: 7.8644663 | G83: 9.5761039
A84: Cash & ST Inv/Current Assets (%) | B84: 84.995431 | C84: 84.882711 | D84: 85.435342 | E84: 87.597552 | F84: 81.923921 | G84: 85.137632
A85: CFO/Current Liabilities (%) | B85: 307.85405 | C85: 172.30256 | D85: 153.23194 | E85: 383.81818 | F85: 383.21629 | G85: 446.7013
A87: Coverage (x)
A88: Net Debt/EBITDA | B88: -2.8910181 | C88: -1.5541126 | D88: -6.1246841 | E88: -2.7906918 | F88: -1.7678543 | G88: -2.2177479
A89: Net Debt/(EBITDA-Capex) | C89: -2.1934827 | D89: -- | E89: -4.2696498 | F89: -2.5082342 | G89: -3.2086063
A90: Total Debt/EBITDA | B90: 0.50152983 | C90: 0.32563733 | D90: 1.9848357 | E90: 0.12105799 | F90: 0.03756247 | G90: 0.038555692
A91: EBIT/Interest Expense (Int. Coverage) | B91: 118.16472 | C91: 41.809524 | D91: 10.54902 | E91: 52.160714 | F91: 215.65217 | G91: 270.65217
A92: EBITDA/Interest Expense | B92: 153.58037 | C92: 49.5 | D92: 23.27451 | E92: 70.214286 | F92: 269.69565 | G92: 355.21739
A93: Fixed-charge Coverage Ratio | B93: 118.16472 | C93: 41.809524 | D93: 10.54902 | E93: 52.160714 | F93: 215.65217 | G93: 270.65217
A94: CFO/Interest Expense | B94: 151.00242 | C94: 36.880952 | D94: 31.607843 | E94: 75.392857 | F94: 237.26087 | G94: 373.86957
A95: LT Debt/EBITDA | B95: 0.39226635 | C95: 0.19143819 | D95: 1.6773378 | E95: 0.060274669 | F95: 0.019184266 | G95: 0.013096695
A96: Net Debt/FFO | B96: -2.5760027 | C96: -2.0926166 | D96: -3.4569662 | E96: -3.0944726 | F96: -1.9174681 | G96: -2.3184901
A97: LT Debt/FFO | B97: 0.26117003 | C97: 0.25777202 | D97: 0.94674275 | E97: 0.066835871 | F97: 0.020807834 | G97: 0.013691619
A98: FCF/Total Debt | B98: 8.4824902 | C98: 1.3929099 | D98: 0.16001698 | E98: 6.0084034 | F98: 15.562232 | G98: 19.288889
A99: CFO/Total Debt | B99: 12.512201 | C99: 2.2880355 | D99: 0.68421053 | E99: 8.8697479 | F99: 23.420601 | G99: 27.298413
A101: Leverage (%)
A102: LT Debt/Total Equity | B102: 5.4330473 | C102: 8.124107 | D102: 16.937473 | E102: 1.5319974 | F102: 0.32967642 | G102: 0.2419829
A103: LT Debt/Total Capital | B103: 4.6602785 | C103: 7.1377331 | D103: 14.10956 | E103: 1.4862661 | F103: 0.327562 | G103: 0.24027126
A104: LT Debt/Total Assets | B104: 4.2612875 | C104: 6.2865266 | D104: 13.182811 | E104: 1.3243923 | F104: 0.29613777 | G104: 0.2165685
A105: Total Debt/Total Assets | B105: 6.0340637 | C105: 10.693413 | D105: 15.59955 | E105: 2.6599609 | F105: 0.57983277 | G105: 0.63756148
A106: Net Debt/Total Equity | B106: -54.017141 | C106: -65.952235 | D106: -61.846023 | E106: -70.930834 | F106: -30.380098 | G106: -40.976525
A107: Total Debt/Equity | B107: 7.6592973 | C107: 13.819147 | D107: 20.042535 | E107: 3.0769231 | F107: 0.64550089 | G107: 0.71237957
A108: Net Debt/Total Capital | B108: -49.830056 | C108: -57.944763 | D108: -51.520091 | E108: -68.813496 | F108: -30.185251 | G108: -40.686682
A109: Total Debt/Total Capital | B109: 6.634258 | C109: 12.14132 | D109: 16.696194 | E109: 2.9850746 | F109: 0.6413609 | G109: 0.70734062
